denonavr_serial/__init__.py
denonavr_serial-0.0.1.dist-info/DESCRIPTION.rst
denonavr_serial-0.0.1.dist-info/METADATA
denonavr_serial-0.0.1.dist-info/RECORD
denonavr_serial-0.0.1.dist-info/WHEEL
denonavr_serial-0.0.1.dist-info/metadata.json
denonavr_serial-0.0.1.dist-info/top_level.txt
