Metadata-Version: 2.0
Name: denonavr-serial
Version: 0.0.1
Summary: Library for controlling Denon AVR Receivers via a serial port
Home-page: https://github.com/auchter/denonavr_serial
Author: Michael Auchter
Author-email: a@phire.org
License: MIT
Keywords: denon stereo receiver avr serial rs232
Platform: UNKNOWN
Classifier: Development Status :: 3 - Alpha
Classifier: License :: OSI Approved :: MIT License
Classifier: Programming Language :: Python :: 3.4
